manim_themes/docbuild/__init__.py
manim_themes/docbuild/manta_directive.py
manim_themes/logger.py
manim_themes/manim_theme.py
manim_themes/theme_preview.py
manim_themes-0.1.3.dist-info/METADATA
manim_themes-0.1.3.dist-info/WHEEL
manim_themes-0.1.3.dist-info/RECORD
