Metadata-Version: 2.3
Name: manim-themes
Version: 0.1.3
Summary: A Manim plugin that lets you apply a iterm2 color theme to your Manim scenes.
License: MIT
Author: Alexander Nasuta
Author-email: alexander.nasuta@wzl-iqs.rwth-aachen.de
Requires-Python: >=3.11,<4.0
Classifier: License :: OSI Approved :: MIT License
Classifier: Programming Language :: Python :: 3
Classifier: Programming Language :: Python :: 3.11
Classifier: Programming Language :: Python :: 3.12
Classifier: Programming Language :: Python :: 3.13
Requires-Dist: manim (>=0.19.0,<0.20.0)
Project-URL: Documentation, https://manim-themes.readthedocs.io/en/latest/
Project-URL: Homepage, https://github.com/Alexander-Nasuta/manim-themes
Project-URL: Repository, https://github.com/Alexander-Nasuta/manim-themes
